array2gif/__init__.py
array2gif/core.py
array2gif-1.0.4.dist-info/METADATA
array2gif-1.0.4.dist-info/RECORD
array2gif-1.0.4.dist-info/WHEEL
array2gif-1.0.4.dist-info/top_level.txt
