Metadata-Version: 1.1
Name: array2gif
Version: 1.0.4
Summary: Write a (list of) NumPy array(s) to an (animated) GIF.
Home-page: https://github.com/tanyaschlusser/array2gif
Author: Tanya Schlusser
Author-email: tanya@tickel.net
License: BSD
Keywords: array2gif animated gif encoder numpy rgb
Platform: UNKNOWN
Classifier: Development Status :: 5 - Production/Stable
Classifier: Intended Audience :: Developers
Classifier: Intended Audience :: Science/Research
Classifier: License :: OSI Approved :: BSD License
Classifier: Programming Language :: Python :: 2
Classifier: Programming Language :: Python :: 2.7
Classifier: Programming Language :: Python :: 3
Classifier: Programming Language :: Python :: 3.4
Classifier: Programming Language :: Python :: 3.5
Classifier: Programming Language :: Python :: 3.6
Classifier: Programming Language :: Python :: Implementation :: CPython
Classifier: Operating System :: OS Independent
Classifier: Topic :: Scientific/Engineering :: Visualization
